setup.cfg
setup.py
ticker/__init__.py
ticker/ticker.py
ticker/ticker_api.py
ticker/ticker_utils.py
ticker.egg-info/PKG-INFO
ticker.egg-info/SOURCES.txt
ticker.egg-info/dependency_links.txt
ticker.egg-info/not-zip-safe
ticker.egg-info/requires.txt
ticker.egg-info/top_level.txt