Metadata-Version: 1.0
Name: ticker
Version: 0.12
Summary: Yahoo finance wrapper for stock information
Home-page: http://github.com/stefankopieczek/ticker
Author: Stefan Kopieczek
Author-email: stefankopieczek+ticker@gmail.com
License: LGPL 2.0
Platform: UNKNOWN
